{"_zone": "America/Moncton",
"zone": [
	{
		"_from": "-9999-01-01T00:00:00Z",
		"from": -377711769600000,
		"_to": "1883-12-09T04:19:08Z",
		"to": -2715882052000,
		"dst": false,
		"offset": -15548,
		"name": "LMT"
	},
	{
		"_from": "1883-12-09T04:19:08Z",
		"from": -2715882052000,
		"_to": "1902-06-15T05:00:00Z",
		"to": -2131642800000,
		"dst": false,
		"offset": -18000,
		"name": "EST"
	},
	{
		"_from": "1902-06-15T05:00:00Z",
		"from": -2131642800000,
		"_to": "1918-04-14T06:00:00Z",
		"to": -1632074400000,
		"dst": false,
		"offset": -14400,
		"name": "AT"
	},
	{
		"_from": "1918-04-14T06:00:00Z",
		"from": -1632074400000,
		"_to": "1918-10-31T05:00:00Z",
		"to": -1614798000000,
		"dst": true,
		"offset": -10800,
		"name": "ADT"
	},
	{
		"_from": "1918-10-31T05:00:00Z",
		"from": -1614798000000,
		"_to": "1933-01-01T04:00:00Z",
		"to": -1167595200000,
		"dst": false,
		"offset": -14400,
		"name": "AST"
	},
	{
		"_from": "1933-01-01T04:00:00Z",
		"from": -1167595200000,
		"_to": "1933-06-11T05:00:00Z",
		"to": -1153681200000,
		"dst": false,
		"offset": -14400,
		"name": "AT"
	},
	{
		"_from": "1933-06-11T05:00:00Z",
		"from": -1153681200000,
		"_to": "1933-09-10T04:00:00Z",
		"to": -1145822400000,
		"dst": true,
		"offset": -10800,
		"name": "ADT"
	},
	{
		"_from": "1933-09-10T04:00:00Z",
		"from": -1145822400000,
		"_to": "1934-06-10T05:00:00Z",
		"to": -1122231600000,
		"dst": false,
		"offset": -14400,
		"name": "AST"
	},
	{
		"_from": "1934-06-10T05:00:00Z",
		"from": -1122231600000,
		"_to": "1934-09-09T04:00:00Z",
		"to": -1114372800000,
		"dst": true,
		"offset": -10800,
		"name": "ADT"
	},
	{
		"_from": "1934-09-09T04:00:00Z",
		"from": -1114372800000,
		"_to": "1935-06-09T05:00:00Z",
		"to": -1090782000000,
		"dst": false,
		"offset": -14400,
		"name": "AST"
	},
	{
		"_from": "1935-06-09T05:00:00Z",
		"from": -1090782000000,
		"_to": "1935-09-08T04:00:00Z",
		"to": -1082923200000,
		"dst": true,
		"offset": -10800,
		"name": "ADT"
	},
	{
		"_from": "1935-09-08T04:00:00Z",
		"from": -1082923200000,
		"_to": "1936-06-07T05:00:00Z",
		"to": -1059332400000,
		"dst": false,
		"offset": -14400,
		"name": "AST"
	},
	{
		"_from": "1936-06-07T05:00:00Z",
		"from": -1059332400000,
		"_to": "1936-09-06T04:00:00Z",
		"to": -1051473600000,
		"dst": true,
		"offset": -10800,
		"name": "ADT"
	},
	{
		"_from": "1936-09-06T04:00:00Z",
		"from": -1051473600000,
		"_to": "1937-06-06T05:00:00Z",
		"to": -1027882800000,
		"dst": false,
		"offset": -14400,
		"name": "AST"
	},
	{
		"_from": "1937-06-06T05:00:00Z",
		"from": -1027882800000,
		"_to": "1937-09-05T04:00:00Z",
		"to": -1020024000000,
		"dst": true,
		"offset": -10800,
		"name": "ADT"
	},
	{
		"_from": "1937-09-05T04:00:00Z",
		"from": -1020024000000,
		"_to": "1938-06-05T05:00:00Z",
		"to": -996433200000,
		"dst": false,
		"offset": -14400,
		"name": "AST"
	},
	{
		"_from": "1938-06-05T05:00:00Z",
		"from": -996433200000,
		"_to": "1938-09-04T04:00:00Z",
		"to": -988574400000,
		"dst": true,
		"offset": -10800,
		"name": "ADT"
	},
	{
		"_from": "1938-09-04T04:00:00Z",
		"from": -988574400000,
		"_to": "1939-05-27T05:00:00Z",
		"to": -965674800000,
		"dst": false,
		"offset": -14400,
		"name": "AST"
	},
	{
		"_from": "1939-05-27T05:00:00Z",
		"from": -965674800000,
		"_to": "1939-09-23T04:00:00Z",
		"to": -955396800000,
		"dst": true,
		"offset": -10800,
		"name": "ADT"
	},
	{
		"_from": "1939-09-23T04:00:00Z",
		"from": -955396800000,
		"_to": "1940-05-19T05:00:00Z",
		"to": -934743600000,
		"dst": false,
		"offset": -14400,
		"name": "AST"
	},
	{
		"_from": "1940-05-19T05:00:00Z",
		"from": -934743600000,
		"_to": "1940-09-21T04:00:00Z",
		"to": -923947200000,
		"dst": true,
		"offset": -10800,
		"name": "ADT"
	},
	{
		"_from": "1940-09-21T04:00:00Z",
		"from": -923947200000,
		"_to": "1941-05-04T05:00:00Z",
		"to": -904503600000,
		"dst": false,
		"offset": -14400,
		"name": "AST"
	},
	{
		"_from": "1941-05-04T05:00:00Z",
		"from": -904503600000,
		"_to": "1941-09-27T04:00:00Z",
		"to": -891892800000,
		"dst": true,
		"offset": -10800,
		"name": "ADT"
	},
	{
		"_from": "1941-09-27T04:00:00Z",
		"from": -891892800000,
		"_to": "1942-01-01T04:00:00Z",
		"to": -883598400000,
		"dst": false,
		"offset": -14400,
		"name": "AST"
	},
	{
		"_from": "1942-01-01T04:00:00Z",
		"from": -883598400000,
		"_to": "1942-02-09T06:00:00Z",
		"to": -880221600000,
		"dst": false,
		"offset": -14400,
		"name": "AT"
	},
	{
		"_from": "1942-02-09T06:00:00Z",
		"from": -880221600000,
		"_to": "1945-08-14T23:00:00Z",
		"to": -769395600000,
		"dst": true,
		"offset": -10800,
		"name": "AWT"
	},
	{
		"_from": "1945-08-14T23:00:00Z",
		"from": -769395600000,
		"_to": "1945-09-30T05:00:00Z",
		"to": -765399600000,
		"dst": true,
		"offset": -10800,
		"name": "APT"
	},
	{
		"_from": "1945-09-30T05:00:00Z",
		"from": -765399600000,
		"_to": "1946-01-01T04:00:00Z",
		"to": -757368000000,
		"dst": false,
		"offset": -14400,
		"name": "AST"
	},
	{
		"_from": "1946-01-01T04:00:00Z",
		"from": -757368000000,
		"_to": "1946-04-28T06:00:00Z",
		"to": -747252000000,
		"dst": false,
		"offset": -14400,
		"name": "AT"
	},
	{
		"_from": "1946-04-28T06:00:00Z",
		"from": -747252000000,
		"_to": "1946-09-29T05:00:00Z",
		"to": -733950000000,
		"dst": true,
		"offset": -10800,
		"name": "ADT"
	},
	{
		"_from": "1946-09-29T05:00:00Z",
		"from": -733950000000,
		"_to": "1947-04-27T06:00:00Z",
		"to": -715802400000,
		"dst": false,
		"offset": -14400,
		"name": "AST"
	},
	{
		"_from": "1947-04-27T06:00:00Z",
		"from": -715802400000,
		"_to": "1947-09-28T05:00:00Z",
		"to": -702500400000,
		"dst": true,
		"offset": -10800,
		"name": "ADT"
	},
	{
		"_from": "1947-09-28T05:00:00Z",
		"from": -702500400000,
		"_to": "1948-04-25T06:00:00Z",
		"to": -684352800000,
		"dst": false,
		"offset": -14400,
		"name": "AST"
	},
	{
		"_from": "1948-04-25T06:00:00Z",
		"from": -684352800000,
		"_to": "1948-09-26T05:00:00Z",
		"to": -671050800000,
		"dst": true,
		"offset": -10800,
		"name": "ADT"
	},
	{
		"_from": "1948-09-26T05:00:00Z",
		"from": -671050800000,
		"_to": "1949-04-24T06:00:00Z",
		"to": -652903200000,
		"dst": false,
		"offset": -14400,
		"name": "AST"
	},
	{
		"_from": "1949-04-24T06:00:00Z",
		"from": -652903200000,
		"_to": "1949-09-25T05:00:00Z",
		"to": -639601200000,
		"dst": true,
		"offset": -10800,
		"name": "ADT"
	},
	{
		"_from": "1949-09-25T05:00:00Z",
		"from": -639601200000,
		"_to": "1950-04-30T06:00:00Z",
		"to": -620848800000,
		"dst": false,
		"offset": -14400,
		"name": "AST"
	},
	{
		"_from": "1950-04-30T06:00:00Z",
		"from": -620848800000,
		"_to": "1950-09-24T05:00:00Z",
		"to": -608151600000,
		"dst": true,
		"offset": -10800,
		"name": "ADT"
	},
	{
		"_from": "1950-09-24T05:00:00Z",
		"from": -608151600000,
		"_to": "1951-04-29T06:00:00Z",
		"to": -589399200000,
		"dst": false,
		"offset": -14400,
		"name": "AST"
	},
	{
		"_from": "1951-04-29T06:00:00Z",
		"from": -589399200000,
		"_to": "1951-09-30T05:00:00Z",
		"to": -576097200000,
		"dst": true,
		"offset": -10800,
		"name": "ADT"
	},
	{
		"_from": "1951-09-30T05:00:00Z",
		"from": -576097200000,
		"_to": "1952-04-27T06:00:00Z",
		"to": -557949600000,
		"dst": false,
		"offset": -14400,
		"name": "AST"
	},
	{
		"_from": "1952-04-27T06:00:00Z",
		"from": -557949600000,
		"_to": "1952-09-28T05:00:00Z",
		"to": -544647600000,
		"dst": true,
		"offset": -10800,
		"name": "ADT"
	},
	{
		"_from": "1952-09-28T05:00:00Z",
		"from": -544647600000,
		"_to": "1953-04-26T06:00:00Z",
		"to": -526500000000,
		"dst": false,
		"offset": -14400,
		"name": "AST"
	},
	{
		"_from": "1953-04-26T06:00:00Z",
		"from": -526500000000,
		"_to": "1953-09-27T05:00:00Z",
		"to": -513198000000,
		"dst": true,
		"offset": -10800,
		"name": "ADT"
	},
	{
		"_from": "1953-09-27T05:00:00Z",
		"from": -513198000000,
		"_to": "1954-04-25T06:00:00Z",
		"to": -495050400000,
		"dst": false,
		"offset": -14400,
		"name": "AST"
	},
	{
		"_from": "1954-04-25T06:00:00Z",
		"from": -495050400000,
		"_to": "1954-09-26T05:00:00Z",
		"to": -481748400000,
		"dst": true,
		"offset": -10800,
		"name": "ADT"
	},
	{
		"_from": "1954-09-26T05:00:00Z",
		"from": -481748400000,
		"_to": "1955-04-24T06:00:00Z",
		"to": -463600800000,
		"dst": false,
		"offset": -14400,
		"name": "AST"
	},
	{
		"_from": "1955-04-24T06:00:00Z",
		"from": -463600800000,
		"_to": "1955-09-25T05:00:00Z",
		"to": -450298800000,
		"dst": true,
		"offset": -10800,
		"name": "ADT"
	},
	{
		"_from": "1955-09-25T05:00:00Z",
		"from": -450298800000,
		"_to": "1956-04-29T06:00:00Z",
		"to": -431546400000,
		"dst": false,
		"offset": -14400,
		"name": "AST"
	},
	{
		"_from": "1956-04-29T06:00:00Z",
		"from": -431546400000,
		"_to": "1956-09-30T05:00:00Z",
		"to": -418244400000,
		"dst": true,
		"offset": -10800,
		"name": "ADT"
	},
	{
		"_from": "1956-09-30T05:00:00Z",
		"from": -418244400000,
		"_to": "1957-04-28T06:00:00Z",
		"to": -400096800000,
		"dst": false,
		"offset": -14400,
		"name": "AST"
	},
	{
		"_from": "1957-04-28T06:00:00Z",
		"from": -400096800000,
		"_to": "1957-10-27T05:00:00Z",
		"to": -384375600000,
		"dst": true,
		"offset": -10800,
		"name": "ADT"
	},
	{
		"_from": "1957-10-27T05:00:00Z",
		"from": -384375600000,
		"_to": "1958-04-27T06:00:00Z",
		"to": -368647200000,
		"dst": false,
		"offset": -14400,
		"name": "AST"
	},
	{
		"_from": "1958-04-27T06:00:00Z",
		"from": -368647200000,
		"_to": "1958-10-26T05:00:00Z",
		"to": -352926000000,
		"dst": true,
		"offset": -10800,
		"name": "ADT"
	},
	{
		"_from": "1958-10-26T05:00:00Z",
		"from": -352926000000,
		"_to": "1959-04-26T06:00:00Z",
		"to": -337197600000,
		"dst": false,
		"offset": -14400,
		"name": "AST"
	},
	{
		"_from": "1959-04-26T06:00:00Z",
		"from": -337197600000,
		"_to": "1959-10-25T05:00:00Z",
		"to": -321476400000,
		"dst": true,
		"offset": -10800,
		"name": "ADT"
	},
	{
		"_from": "1959-10-25T05:00:00Z",
		"from": -321476400000,
		"_to": "1960-04-24T06:00:00Z",
		"to": -305748000000,
		"dst": false,
		"offset": -14400,
		"name": "AST"
	},
	{
		"_from": "1960-04-24T06:00:00Z",
		"from": -305748000000,
		"_to": "1960-10-30T05:00:00Z",
		"to": -289422000000,
		"dst": true,
		"offset": -10800,
		"name": "ADT"
	},
	{
		"_from": "1960-10-30T05:00:00Z",
		"from": -289422000000,
		"_to": "1961-04-30T06:00:00Z",
		"to": -273693600000,
		"dst": false,
		"offset": -14400,
		"name": "AST"
	},
	{
		"_from": "1961-04-30T06:00:00Z",
		"from": -273693600000,
		"_to": "1961-10-29T05:00:00Z",
		"to": -257972400000,
		"dst": true,
		"offset": -10800,
		"name": "ADT"
	},
	{
		"_from": "1961-10-29T05:00:00Z",
		"from": -257972400000,
		"_to": "1962-04-29T06:00:00Z",
		"to": -242244000000,
		"dst": false,
		"offset": -14400,
		"name": "AST"
	},
	{
		"_from": "1962-04-29T06:00:00Z",
		"from": -242244000000,
		"_to": "1962-10-28T05:00:00Z",
		"to": -226522800000,
		"dst": true,
		"offset": -10800,
		"name": "ADT"
	},
	{
		"_from": "1962-10-28T05:00:00Z",
		"from": -226522800000,
		"_to": "1963-04-28T06:00:00Z",
		"to": -210794400000,
		"dst": false,
		"offset": -14400,
		"name": "AST"
	},
	{
		"_from": "1963-04-28T06:00:00Z",
		"from": -210794400000,
		"_to": "1963-10-27T05:00:00Z",
		"to": -195073200000,
		"dst": true,
		"offset": -10800,
		"name": "ADT"
	},
	{
		"_from": "1963-10-27T05:00:00Z",
		"from": -195073200000,
		"_to": "1964-04-26T06:00:00Z",
		"to": -179344800000,
		"dst": false,
		"offset": -14400,
		"name": "AST"
	},
	{
		"_from": "1964-04-26T06:00:00Z",
		"from": -179344800000,
		"_to": "1964-10-25T05:00:00Z",
		"to": -163623600000,
		"dst": true,
		"offset": -10800,
		"name": "ADT"
	},
	{
		"_from": "1964-10-25T05:00:00Z",
		"from": -163623600000,
		"_to": "1965-04-25T06:00:00Z",
		"to": -147895200000,
		"dst": false,
		"offset": -14400,
		"name": "AST"
	},
	{
		"_from": "1965-04-25T06:00:00Z",
		"from": -147895200000,
		"_to": "1965-10-31T05:00:00Z",
		"to": -131569200000,
		"dst": true,
		"offset": -10800,
		"name": "ADT"
	},
	{
		"_from": "1965-10-31T05:00:00Z",
		"from": -131569200000,
		"_to": "1966-04-24T06:00:00Z",
		"to": -116445600000,
		"dst": false,
		"offset": -14400,
		"name": "AST"
	},
	{
		"_from": "1966-04-24T06:00:00Z",
		"from": -116445600000,
		"_to": "1966-10-30T05:00:00Z",
		"to": -100119600000,
		"dst": true,
		"offset": -10800,
		"name": "ADT"
	},
	{
		"_from": "1966-10-30T05:00:00Z",
		"from": -100119600000,
		"_to": "1967-04-30T06:00:00Z",
		"to": -84391200000,
		"dst": false,
		"offset": -14400,
		"name": "AST"
	},
	{
		"_from": "1967-04-30T06:00:00Z",
		"from": -84391200000,
		"_to": "1967-10-29T05:00:00Z",
		"to": -68670000000,
		"dst": true,
		"offset": -10800,
		"name": "ADT"
	},
	{
		"_from": "1967-10-29T05:00:00Z",
		"from": -68670000000,
		"_to": "1968-04-28T06:00:00Z",
		"to": -52941600000,
		"dst": false,
		"offset": -14400,
		"name": "AST"
	},
	{
		"_from": "1968-04-28T06:00:00Z",
		"from": -52941600000,
		"_to": "1968-10-27T05:00:00Z",
		"to": -37220400000,
		"dst": true,
		"offset": -10800,
		"name": "ADT"
	},
	{
		"_from": "1968-10-27T05:00:00Z",
		"from": -37220400000,
		"_to": "1969-04-27T06:00:00Z",
		"to": -21492000000,
		"dst": false,
		"offset": -14400,
		"name": "AST"
	},
	{
		"_from": "1969-04-27T06:00:00Z",
		"from": -21492000000,
		"_to": "1969-10-26T05:00:00Z",
		"to": -5770800000,
		"dst": true,
		"offset": -10800,
		"name": "ADT"
	},
	{
		"_from": "1969-10-26T05:00:00Z",
		"from": -5770800000,
		"_to": "1970-04-26T06:00:00Z",
		"to": 9957600000,
		"dst": false,
		"offset": -14400,
		"name": "AST"
	},
	{
		"_from": "1970-04-26T06:00:00Z",
		"from": 9957600000,
		"_to": "1970-10-25T05:00:00Z",
		"to": 25678800000,
		"dst": true,
		"offset": -10800,
		"name": "ADT"
	},
	{
		"_from": "1970-10-25T05:00:00Z",
		"from": 25678800000,
		"_to": "1971-04-25T06:00:00Z",
		"to": 41407200000,
		"dst": false,
		"offset": -14400,
		"name": "AST"
	},
	{
		"_from": "1971-04-25T06:00:00Z",
		"from": 41407200000,
		"_to": "1971-10-31T05:00:00Z",
		"to": 57733200000,
		"dst": true,
		"offset": -10800,
		"name": "ADT"
	},
	{
		"_from": "1971-10-31T05:00:00Z",
		"from": 57733200000,
		"_to": "1972-04-30T06:00:00Z",
		"to": 73461600000,
		"dst": false,
		"offset": -14400,
		"name": "AST"
	},
	{
		"_from": "1972-04-30T06:00:00Z",
		"from": 73461600000,
		"_to": "1972-10-29T05:00:00Z",
		"to": 89182800000,
		"dst": true,
		"offset": -10800,
		"name": "ADT"
	},
	{
		"_from": "1972-10-29T05:00:00Z",
		"from": 89182800000,
		"_to": "1973-01-01T04:00:00Z",
		"to": 94708800000,
		"dst": false,
		"offset": -14400,
		"name": "AST"
	},
	{
		"_from": "1973-01-01T04:00:00Z",
		"from": 94708800000,
		"_to": "1974-04-28T06:00:00Z",
		"to": 136360800000,
		"dst": false,
		"offset": -14400,
		"name": "AT"
	},
	{
		"_from": "1974-04-28T06:00:00Z",
		"from": 136360800000,
		"_to": "1974-10-27T05:00:00Z",
		"to": 152082000000,
		"dst": true,
		"offset": -10800,
		"name": "ADT"
	},
	{
		"_from": "1974-10-27T05:00:00Z",
		"from": 152082000000,
		"_to": "1975-04-27T06:00:00Z",
		"to": 167810400000,
		"dst": false,
		"offset": -14400,
		"name": "AST"
	},
	{
		"_from": "1975-04-27T06:00:00Z",
		"from": 167810400000,
		"_to": "1975-10-26T05:00:00Z",
		"to": 183531600000,
		"dst": true,
		"offset": -10800,
		"name": "ADT"
	},
	{
		"_from": "1975-10-26T05:00:00Z",
		"from": 183531600000,
		"_to": "1976-04-25T06:00:00Z",
		"to": 199260000000,
		"dst": false,
		"offset": -14400,
		"name": "AST"
	},
	{
		"_from": "1976-04-25T06:00:00Z",
		"from": 199260000000,
		"_to": "1976-10-31T05:00:00Z",
		"to": 215586000000,
		"dst": true,
		"offset": -10800,
		"name": "ADT"
	},
	{
		"_from": "1976-10-31T05:00:00Z",
		"from": 215586000000,
		"_to": "1977-04-24T06:00:00Z",
		"to": 230709600000,
		"dst": false,
		"offset": -14400,
		"name": "AST"
	},
	{
		"_from": "1977-04-24T06:00:00Z",
		"from": 230709600000,
		"_to": "1977-10-30T05:00:00Z",
		"to": 247035600000,
		"dst": true,
		"offset": -10800,
		"name": "ADT"
	},
	{
		"_from": "1977-10-30T05:00:00Z",
		"from": 247035600000,
		"_to": "1978-04-30T06:00:00Z",
		"to": 262764000000,
		"dst": false,
		"offset": -14400,
		"name": "AST"
	},
	{
		"_from": "1978-04-30T06:00:00Z",
		"from": 262764000000,
		"_to": "1978-10-29T05:00:00Z",
		"to": 278485200000,
		"dst": true,
		"offset": -10800,
		"name": "ADT"
	},
	{
		"_from": "1978-10-29T05:00:00Z",
		"from": 278485200000,
		"_to": "1979-04-29T06:00:00Z",
		"to": 294213600000,
		"dst": false,
		"offset": -14400,
		"name": "AST"
	},
	{
		"_from": "1979-04-29T06:00:00Z",
		"from": 294213600000,
		"_to": "1979-10-28T05:00:00Z",
		"to": 309934800000,
		"dst": true,
		"offset": -10800,
		"name": "ADT"
	},
	{
		"_from": "1979-10-28T05:00:00Z",
		"from": 309934800000,
		"_to": "1980-04-27T06:00:00Z",
		"to": 325663200000,
		"dst": false,
		"offset": -14400,
		"name": "AST"
	},
	{
		"_from": "1980-04-27T06:00:00Z",
		"from": 325663200000,
		"_to": "1980-10-26T05:00:00Z",
		"to": 341384400000,
		"dst": true,
		"offset": -10800,
		"name": "ADT"
	},
	{
		"_from": "1980-10-26T05:00:00Z",
		"from": 341384400000,
		"_to": "1981-04-26T06:00:00Z",
		"to": 357112800000,
		"dst": false,
		"offset": -14400,
		"name": "AST"
	},
	{
		"_from": "1981-04-26T06:00:00Z",
		"from": 357112800000,
		"_to": "1981-10-25T05:00:00Z",
		"to": 372834000000,
		"dst": true,
		"offset": -10800,
		"name": "ADT"
	},
	{
		"_from": "1981-10-25T05:00:00Z",
		"from": 372834000000,
		"_to": "1982-04-25T06:00:00Z",
		"to": 388562400000,
		"dst": false,
		"offset": -14400,
		"name": "AST"
	},
	{
		"_from": "1982-04-25T06:00:00Z",
		"from": 388562400000,
		"_to": "1982-10-31T05:00:00Z",
		"to": 404888400000,
		"dst": true,
		"offset": -10800,
		"name": "ADT"
	},
	{
		"_from": "1982-10-31T05:00:00Z",
		"from": 404888400000,
		"_to": "1983-04-24T06:00:00Z",
		"to": 420012000000,
		"dst": false,
		"offset": -14400,
		"name": "AST"
	},
	{
		"_from": "1983-04-24T06:00:00Z",
		"from": 420012000000,
		"_to": "1983-10-30T05:00:00Z",
		"to": 436338000000,
		"dst": true,
		"offset": -10800,
		"name": "ADT"
	},
	{
		"_from": "1983-10-30T05:00:00Z",
		"from": 436338000000,
		"_to": "1984-04-29T06:00:00Z",
		"to": 452066400000,
		"dst": false,
		"offset": -14400,
		"name": "AST"
	},
	{
		"_from": "1984-04-29T06:00:00Z",
		"from": 452066400000,
		"_to": "1984-10-28T05:00:00Z",
		"to": 467787600000,
		"dst": true,
		"offset": -10800,
		"name": "ADT"
	},
	{
		"_from": "1984-10-28T05:00:00Z",
		"from": 467787600000,
		"_to": "1985-04-28T06:00:00Z",
		"to": 483516000000,
		"dst": false,
		"offset": -14400,
		"name": "AST"
	},
	{
		"_from": "1985-04-28T06:00:00Z",
		"from": 483516000000,
		"_to": "1985-10-27T05:00:00Z",
		"to": 499237200000,
		"dst": true,
		"offset": -10800,
		"name": "ADT"
	},
	{
		"_from": "1985-10-27T05:00:00Z",
		"from": 499237200000,
		"_to": "1986-04-27T06:00:00Z",
		"to": 514965600000,
		"dst": false,
		"offset": -14400,
		"name": "AST"
	},
	{
		"_from": "1986-04-27T06:00:00Z",
		"from": 514965600000,
		"_to": "1986-10-26T05:00:00Z",
		"to": 530686800000,
		"dst": true,
		"offset": -10800,
		"name": "ADT"
	},
	{
		"_from": "1986-10-26T05:00:00Z",
		"from": 530686800000,
		"_to": "1987-04-05T06:00:00Z",
		"to": 544600800000,
		"dst": false,
		"offset": -14400,
		"name": "AST"
	},
	{
		"_from": "1987-04-05T06:00:00Z",
		"from": 544600800000,
		"_to": "1987-10-25T05:00:00Z",
		"to": 562136400000,
		"dst": true,
		"offset": -10800,
		"name": "ADT"
	},
	{
		"_from": "1987-10-25T05:00:00Z",
		"from": 562136400000,
		"_to": "1988-04-03T06:00:00Z",
		"to": 576050400000,
		"dst": false,
		"offset": -14400,
		"name": "AST"
	},
	{
		"_from": "1988-04-03T06:00:00Z",
		"from": 576050400000,
		"_to": "1988-10-30T05:00:00Z",
		"to": 594190800000,
		"dst": true,
		"offset": -10800,
		"name": "ADT"
	},
	{
		"_from": "1988-10-30T05:00:00Z",
		"from": 594190800000,
		"_to": "1989-04-02T06:00:00Z",
		"to": 607500000000,
		"dst": false,
		"offset": -14400,
		"name": "AST"
	},
	{
		"_from": "1989-04-02T06:00:00Z",
		"from": 607500000000,
		"_to": "1989-10-29T05:00:00Z",
		"to": 625640400000,
		"dst": true,
		"offset": -10800,
		"name": "ADT"
	},
	{
		"_from": "1989-10-29T05:00:00Z",
		"from": 625640400000,
		"_to": "1990-04-01T06:00:00Z",
		"to": 638949600000,
		"dst": false,
		"offset": -14400,
		"name": "AST"
	},
	{
		"_from": "1990-04-01T06:00:00Z",
		"from": 638949600000,
		"_to": "1990-10-28T05:00:00Z",
		"to": 657090000000,
		"dst": true,
		"offset": -10800,
		"name": "ADT"
	},
	{
		"_from": "1990-10-28T05:00:00Z",
		"from": 657090000000,
		"_to": "1991-04-07T06:00:00Z",
		"to": 671004000000,
		"dst": false,
		"offset": -14400,
		"name": "AST"
	},
	{
		"_from": "1991-04-07T06:00:00Z",
		"from": 671004000000,
		"_to": "1991-10-27T05:00:00Z",
		"to": 688539600000,
		"dst": true,
		"offset": -10800,
		"name": "ADT"
	},
	{
		"_from": "1991-10-27T05:00:00Z",
		"from": 688539600000,
		"_to": "1992-04-05T06:00:00Z",
		"to": 702453600000,
		"dst": false,
		"offset": -14400,
		"name": "AST"
	},
	{
		"_from": "1992-04-05T06:00:00Z",
		"from": 702453600000,
		"_to": "1992-10-25T05:00:00Z",
		"to": 719989200000,
		"dst": true,
		"offset": -10800,
		"name": "ADT"
	},
	{
		"_from": "1992-10-25T05:00:00Z",
		"from": 719989200000,
		"_to": "1993-01-01T04:00:00Z",
		"to": 725860800000,
		"dst": false,
		"offset": -14400,
		"name": "AST"
	},
	{
		"_from": "1993-01-01T04:00:00Z",
		"from": 725860800000,
		"_to": "1993-04-04T04:01:00Z",
		"to": 733896060000,
		"dst": false,
		"offset": -14400,
		"name": "AT"
	},
	{
		"_from": "1993-04-04T04:01:00Z",
		"from": 733896060000,
		"_to": "1993-10-31T03:01:00Z",
		"to": 752036460000,
		"dst": true,
		"offset": -10800,
		"name": "ADT"
	},
	{
		"_from": "1993-10-31T03:01:00Z",
		"from": 752036460000,
		"_to": "1994-04-03T04:01:00Z",
		"to": 765345660000,
		"dst": false,
		"offset": -14400,
		"name": "AST"
	},
	{
		"_from": "1994-04-03T04:01:00Z",
		"from": 765345660000,
		"_to": "1994-10-30T03:01:00Z",
		"to": 783486060000,
		"dst": true,
		"offset": -10800,
		"name": "ADT"
	},
	{
		"_from": "1994-10-30T03:01:00Z",
		"from": 783486060000,
		"_to": "1995-04-02T04:01:00Z",
		"to": 796795260000,
		"dst": false,
		"offset": -14400,
		"name": "AST"
	},
	{
		"_from": "1995-04-02T04:01:00Z",
		"from": 796795260000,
		"_to": "1995-10-29T03:01:00Z",
		"to": 814935660000,
		"dst": true,
		"offset": -10800,
		"name": "ADT"
	},
	{
		"_from": "1995-10-29T03:01:00Z",
		"from": 814935660000,
		"_to": "1996-04-07T04:01:00Z",
		"to": 828849660000,
		"dst": false,
		"offset": -14400,
		"name": "AST"
	},
	{
		"_from": "1996-04-07T04:01:00Z",
		"from": 828849660000,
		"_to": "1996-10-27T03:01:00Z",
		"to": 846385260000,
		"dst": true,
		"offset": -10800,
		"name": "ADT"
	},
	{
		"_from": "1996-10-27T03:01:00Z",
		"from": 846385260000,
		"_to": "1997-04-06T04:01:00Z",
		"to": 860299260000,
		"dst": false,
		"offset": -14400,
		"name": "AST"
	},
	{
		"_from": "1997-04-06T04:01:00Z",
		"from": 860299260000,
		"_to": "1997-10-26T03:01:00Z",
		"to": 877834860000,
		"dst": true,
		"offset": -10800,
		"name": "ADT"
	},
	{
		"_from": "1997-10-26T03:01:00Z",
		"from": 877834860000,
		"_to": "1998-04-05T04:01:00Z",
		"to": 891748860000,
		"dst": false,
		"offset": -14400,
		"name": "AST"
	},
	{
		"_from": "1998-04-05T04:01:00Z",
		"from": 891748860000,
		"_to": "1998-10-25T03:01:00Z",
		"to": 909284460000,
		"dst": true,
		"offset": -10800,
		"name": "ADT"
	},
	{
		"_from": "1998-10-25T03:01:00Z",
		"from": 909284460000,
		"_to": "1999-04-04T04:01:00Z",
		"to": 923198460000,
		"dst": false,
		"offset": -14400,
		"name": "AST"
	},
	{
		"_from": "1999-04-04T04:01:00Z",
		"from": 923198460000,
		"_to": "1999-10-31T03:01:00Z",
		"to": 941338860000,
		"dst": true,
		"offset": -10800,
		"name": "ADT"
	},
	{
		"_from": "1999-10-31T03:01:00Z",
		"from": 941338860000,
		"_to": "2000-04-02T04:01:00Z",
		"to": 954648060000,
		"dst": false,
		"offset": -14400,
		"name": "AST"
	},
	{
		"_from": "2000-04-02T04:01:00Z",
		"from": 954648060000,
		"_to": "2000-10-29T03:01:00Z",
		"to": 972788460000,
		"dst": true,
		"offset": -10800,
		"name": "ADT"
	},
	{
		"_from": "2000-10-29T03:01:00Z",
		"from": 972788460000,
		"_to": "2001-04-01T04:01:00Z",
		"to": 986097660000,
		"dst": false,
		"offset": -14400,
		"name": "AST"
	},
	{
		"_from": "2001-04-01T04:01:00Z",
		"from": 986097660000,
		"_to": "2001-10-28T03:01:00Z",
		"to": 1004238060000,
		"dst": true,
		"offset": -10800,
		"name": "ADT"
	},
	{
		"_from": "2001-10-28T03:01:00Z",
		"from": 1004238060000,
		"_to": "2002-04-07T04:01:00Z",
		"to": 1018152060000,
		"dst": false,
		"offset": -14400,
		"name": "AST"
	},
	{
		"_from": "2002-04-07T04:01:00Z",
		"from": 1018152060000,
		"_to": "2002-10-27T03:01:00Z",
		"to": 1035687660000,
		"dst": true,
		"offset": -10800,
		"name": "ADT"
	},
	{
		"_from": "2002-10-27T03:01:00Z",
		"from": 1035687660000,
		"_to": "2003-04-06T04:01:00Z",
		"to": 1049601660000,
		"dst": false,
		"offset": -14400,
		"name": "AST"
	},
	{
		"_from": "2003-04-06T04:01:00Z",
		"from": 1049601660000,
		"_to": "2003-10-26T03:01:00Z",
		"to": 1067137260000,
		"dst": true,
		"offset": -10800,
		"name": "ADT"
	},
	{
		"_from": "2003-10-26T03:01:00Z",
		"from": 1067137260000,
		"_to": "2004-04-04T04:01:00Z",
		"to": 1081051260000,
		"dst": false,
		"offset": -14400,
		"name": "AST"
	},
	{
		"_from": "2004-04-04T04:01:00Z",
		"from": 1081051260000,
		"_to": "2004-10-31T03:01:00Z",
		"to": 1099191660000,
		"dst": true,
		"offset": -10800,
		"name": "ADT"
	},
	{
		"_from": "2004-10-31T03:01:00Z",
		"from": 1099191660000,
		"_to": "2005-04-03T04:01:00Z",
		"to": 1112500860000,
		"dst": false,
		"offset": -14400,
		"name": "AST"
	},
	{
		"_from": "2005-04-03T04:01:00Z",
		"from": 1112500860000,
		"_to": "2005-10-30T03:01:00Z",
		"to": 1130641260000,
		"dst": true,
		"offset": -10800,
		"name": "ADT"
	},
	{
		"_from": "2005-10-30T03:01:00Z",
		"from": 1130641260000,
		"_to": "2006-04-02T04:01:00Z",
		"to": 1143950460000,
		"dst": false,
		"offset": -14400,
		"name": "AST"
	},
	{
		"_from": "2006-04-02T04:01:00Z",
		"from": 1143950460000,
		"_to": "2006-10-29T03:01:00Z",
		"to": 1162090860000,
		"dst": true,
		"offset": -10800,
		"name": "ADT"
	},
	{
		"_from": "2006-10-29T03:01:00Z",
		"from": 1162090860000,
		"_to": "2007-01-01T04:00:00Z",
		"to": 1167624000000,
		"dst": false,
		"offset": -14400,
		"name": "AST"
	},
	{
		"_from": "2007-01-01T04:00:00Z",
		"from": 1167624000000,
		"_to": "2007-03-11T06:00:00Z",
		"to": 1173592800000,
		"dst": false,
		"offset": -14400,
		"name": "AT"
	},
	{
		"_from": "2007-03-11T06:00:00Z",
		"from": 1173592800000,
		"_to": "2007-11-04T05:00:00Z",
		"to": 1194152400000,
		"dst": true,
		"offset": -10800,
		"name": "ADT"
	},
	{
		"_from": "2007-11-04T05:00:00Z",
		"from": 1194152400000,
		"_to": "2008-03-09T06:00:00Z",
		"to": 1205042400000,
		"dst": false,
		"offset": -14400,
		"name": "AST"
	},
	{
		"_from": "2008-03-09T06:00:00Z",
		"from": 1205042400000,
		"_to": "2008-11-02T05:00:00Z",
		"to": 1225602000000,
		"dst": true,
		"offset": -10800,
		"name": "ADT"
	},
	{
		"_from": "2008-11-02T05:00:00Z",
		"from": 1225602000000,
		"_to": "2009-03-08T06:00:00Z",
		"to": 1236492000000,
		"dst": false,
		"offset": -14400,
		"name": "AST"
	},
	{
		"_from": "2009-03-08T06:00:00Z",
		"from": 1236492000000,
		"_to": "2009-11-01T05:00:00Z",
		"to": 1257051600000,
		"dst": true,
		"offset": -10800,
		"name": "ADT"
	},
	{
		"_from": "2009-11-01T05:00:00Z",
		"from": 1257051600000,
		"_to": "2010-03-14T06:00:00Z",
		"to": 1268546400000,
		"dst": false,
		"offset": -14400,
		"name": "AST"
	},
	{
		"_from": "2010-03-14T06:00:00Z",
		"from": 1268546400000,
		"_to": "2010-11-07T05:00:00Z",
		"to": 1289106000000,
		"dst": true,
		"offset": -10800,
		"name": "ADT"
	},
	{
		"_from": "2010-11-07T05:00:00Z",
		"from": 1289106000000,
		"_to": "2011-03-13T06:00:00Z",
		"to": 1299996000000,
		"dst": false,
		"offset": -14400,
		"name": "AST"
	},
	{
		"_from": "2011-03-13T06:00:00Z",
		"from": 1299996000000,
		"_to": "2011-11-06T05:00:00Z",
		"to": 1320555600000,
		"dst": true,
		"offset": -10800,
		"name": "ADT"
	},
	{
		"_from": "2011-11-06T05:00:00Z",
		"from": 1320555600000,
		"_to": "2012-03-11T06:00:00Z",
		"to": 1331445600000,
		"dst": false,
		"offset": -14400,
		"name": "AST"
	},
	{
		"_from": "2012-03-11T06:00:00Z",
		"from": 1331445600000,
		"_to": "2012-11-04T05:00:00Z",
		"to": 1352005200000,
		"dst": true,
		"offset": -10800,
		"name": "ADT"
	},
	{
		"_from": "2012-11-04T05:00:00Z",
		"from": 1352005200000,
		"_to": "2013-03-10T06:00:00Z",
		"to": 1362895200000,
		"dst": false,
		"offset": -14400,
		"name": "AST"
	},
	{
		"_from": "2013-03-10T06:00:00Z",
		"from": 1362895200000,
		"_to": "2013-11-03T05:00:00Z",
		"to": 1383454800000,
		"dst": true,
		"offset": -10800,
		"name": "ADT"
	},
	{
		"_from": "2013-11-03T05:00:00Z",
		"from": 1383454800000,
		"_to": "2014-03-09T06:00:00Z",
		"to": 1394344800000,
		"dst": false,
		"offset": -14400,
		"name": "AST"
	},
	{
		"_from": "2014-03-09T06:00:00Z",
		"from": 1394344800000,
		"_to": "2014-11-02T05:00:00Z",
		"to": 1414904400000,
		"dst": true,
		"offset": -10800,
		"name": "ADT"
	},
	{
		"_from": "2014-11-02T05:00:00Z",
		"from": 1414904400000,
		"_to": "2015-03-08T06:00:00Z",
		"to": 1425794400000,
		"dst": false,
		"offset": -14400,
		"name": "AST"
	},
	{
		"_from": "2015-03-08T06:00:00Z",
		"from": 1425794400000,
		"_to": "2015-11-01T05:00:00Z",
		"to": 1446354000000,
		"dst": true,
		"offset": -10800,
		"name": "ADT"
	},
	{
		"_from": "2015-11-01T05:00:00Z",
		"from": 1446354000000,
		"_to": "2016-03-13T06:00:00Z",
		"to": 1457848800000,
		"dst": false,
		"offset": -14400,
		"name": "AST"
	},
	{
		"_from": "2016-03-13T06:00:00Z",
		"from": 1457848800000,
		"_to": "2016-11-06T05:00:00Z",
		"to": 1478408400000,
		"dst": true,
		"offset": -10800,
		"name": "ADT"
	},
	{
		"_from": "2016-11-06T05:00:00Z",
		"from": 1478408400000,
		"_to": "2017-03-12T06:00:00Z",
		"to": 1489298400000,
		"dst": false,
		"offset": -14400,
		"name": "AST"
	},
	{
		"_from": "2017-03-12T06:00:00Z",
		"from": 1489298400000,
		"_to": "2017-11-05T05:00:00Z",
		"to": 1509858000000,
		"dst": true,
		"offset": -10800,
		"name": "ADT"
	},
	{
		"_from": "2017-11-05T05:00:00Z",
		"from": 1509858000000,
		"_to": "2018-03-11T06:00:00Z",
		"to": 1520748000000,
		"dst": false,
		"offset": -14400,
		"name": "AST"
	},
	{
		"_from": "2018-03-11T06:00:00Z",
		"from": 1520748000000,
		"_to": "2018-11-04T05:00:00Z",
		"to": 1541307600000,
		"dst": true,
		"offset": -10800,
		"name": "ADT"
	},
	{
		"_from": "2018-11-04T05:00:00Z",
		"from": 1541307600000,
		"_to": "2019-03-10T06:00:00Z",
		"to": 1552197600000,
		"dst": false,
		"offset": -14400,
		"name": "AST"
	},
	{
		"_from": "2019-03-10T06:00:00Z",
		"from": 1552197600000,
		"_to": "2019-11-03T05:00:00Z",
		"to": 1572757200000,
		"dst": true,
		"offset": -10800,
		"name": "ADT"
	},
	{
		"_from": "2019-11-03T05:00:00Z",
		"from": 1572757200000,
		"_to": "2020-03-08T06:00:00Z",
		"to": 1583647200000,
		"dst": false,
		"offset": -14400,
		"name": "AST"
	},
	{
		"_from": "2020-03-08T06:00:00Z",
		"from": 1583647200000,
		"_to": "2020-11-01T05:00:00Z",
		"to": 1604206800000,
		"dst": true,
		"offset": -10800,
		"name": "ADT"
	},
	{
		"_from": "2020-11-01T05:00:00Z",
		"from": 1604206800000,
		"_to": "2021-03-14T06:00:00Z",
		"to": 1615701600000,
		"dst": false,
		"offset": -14400,
		"name": "AST"
	},
	{
		"_from": "2021-03-14T06:00:00Z",
		"from": 1615701600000,
		"_to": "2021-11-07T05:00:00Z",
		"to": 1636261200000,
		"dst": true,
		"offset": -10800,
		"name": "ADT"
	},
	{
		"_from": "2021-11-07T05:00:00Z",
		"from": 1636261200000,
		"_to": "2022-03-13T06:00:00Z",
		"to": 1647151200000,
		"dst": false,
		"offset": -14400,
		"name": "AST"
	},
	{
		"_from": "2022-03-13T06:00:00Z",
		"from": 1647151200000,
		"_to": "2022-11-06T05:00:00Z",
		"to": 1667710800000,
		"dst": true,
		"offset": -10800,
		"name": "ADT"
	},
	{
		"_from": "2022-11-06T05:00:00Z",
		"from": 1667710800000,
		"_to": "2023-03-12T06:00:00Z",
		"to": 1678600800000,
		"dst": false,
		"offset": -14400,
		"name": "AST"
	},
	{
		"_from": "2023-03-12T06:00:00Z",
		"from": 1678600800000,
		"_to": "2023-11-05T05:00:00Z",
		"to": 1699160400000,
		"dst": true,
		"offset": -10800,
		"name": "ADT"
	},
	{
		"_from": "2023-11-05T05:00:00Z",
		"from": 1699160400000,
		"_to": "2024-03-10T06:00:00Z",
		"to": 1710050400000,
		"dst": false,
		"offset": -14400,
		"name": "AST"
	},
	{
		"_from": "2024-03-10T06:00:00Z",
		"from": 1710050400000,
		"_to": "2024-11-03T05:00:00Z",
		"to": 1730610000000,
		"dst": true,
		"offset": -10800,
		"name": "ADT"
	},
	{
		"_from": "2024-11-03T05:00:00Z",
		"from": 1730610000000,
		"_to": "2025-03-09T06:00:00Z",
		"to": 1741500000000,
		"dst": false,
		"offset": -14400,
		"name": "AST"
	},
	{
		"_from": "2025-03-09T06:00:00Z",
		"from": 1741500000000,
		"_to": "2025-11-02T05:00:00Z",
		"to": 1762059600000,
		"dst": true,
		"offset": -10800,
		"name": "ADT"
	},
	{
		"_from": "2025-11-02T05:00:00Z",
		"from": 1762059600000,
		"_to": "2026-03-08T06:00:00Z",
		"to": 1772949600000,
		"dst": false,
		"offset": -14400,
		"name": "AST"
	},
	{
		"_from": "2026-03-08T06:00:00Z",
		"from": 1772949600000,
		"_to": "2026-11-01T05:00:00Z",
		"to": 1793509200000,
		"dst": true,
		"offset": -10800,
		"name": "ADT"
	},
	{
		"_from": "2026-11-01T05:00:00Z",
		"from": 1793509200000,
		"_to": "2027-03-14T06:00:00Z",
		"to": 1805004000000,
		"dst": false,
		"offset": -14400,
		"name": "AST"
	},
	{
		"_from": "2027-03-14T06:00:00Z",
		"from": 1805004000000,
		"_to": "2027-11-07T05:00:00Z",
		"to": 1825563600000,
		"dst": true,
		"offset": -10800,
		"name": "ADT"
	},
	{
		"_from": "2027-11-07T05:00:00Z",
		"from": 1825563600000,
		"_to": "2028-03-12T06:00:00Z",
		"to": 1836453600000,
		"dst": false,
		"offset": -14400,
		"name": "AST"
	},
	{
		"_from": "2028-03-12T06:00:00Z",
		"from": 1836453600000,
		"_to": "2028-11-05T05:00:00Z",
		"to": 1857013200000,
		"dst": true,
		"offset": -10800,
		"name": "ADT"
	},
	{
		"_from": "2028-11-05T05:00:00Z",
		"from": 1857013200000,
		"_to": "2029-03-11T06:00:00Z",
		"to": 1867903200000,
		"dst": false,
		"offset": -14400,
		"name": "AST"
	},
	{
		"_from": "2029-03-11T06:00:00Z",
		"from": 1867903200000,
		"_to": "2029-11-04T05:00:00Z",
		"to": 1888462800000,
		"dst": true,
		"offset": -10800,
		"name": "ADT"
	},
	{
		"_from": "2029-11-04T05:00:00Z",
		"from": 1888462800000,
		"_to": "2030-03-10T06:00:00Z",
		"to": 1899352800000,
		"dst": false,
		"offset": -14400,
		"name": "AST"
	},
	{
		"_from": "2030-03-10T06:00:00Z",
		"from": 1899352800000,
		"_to": "2030-11-03T05:00:00Z",
		"to": 1919912400000,
		"dst": true,
		"offset": -10800,
		"name": "ADT"
	},
	{
		"_from": "2030-11-03T05:00:00Z",
		"from": 1919912400000,
		"_to": "2031-03-09T06:00:00Z",
		"to": 1930802400000,
		"dst": false,
		"offset": -14400,
		"name": "AST"
	},
	{
		"_from": "2031-03-09T06:00:00Z",
		"from": 1930802400000,
		"_to": "2031-11-02T05:00:00Z",
		"to": 1951362000000,
		"dst": true,
		"offset": -10800,
		"name": "ADT"
	},
	{
		"_from": "2031-11-02T05:00:00Z",
		"from": 1951362000000,
		"_to": "2032-03-14T06:00:00Z",
		"to": 1962856800000,
		"dst": false,
		"offset": -14400,
		"name": "AST"
	},
	{
		"_from": "2032-03-14T06:00:00Z",
		"from": 1962856800000,
		"_to": "2032-11-07T05:00:00Z",
		"to": 1983416400000,
		"dst": true,
		"offset": -10800,
		"name": "ADT"
	},
	{
		"_from": "2032-11-07T05:00:00Z",
		"from": 1983416400000,
		"_to": "2033-03-13T06:00:00Z",
		"to": 1994306400000,
		"dst": false,
		"offset": -14400,
		"name": "AST"
	},
	{
		"_from": "2033-03-13T06:00:00Z",
		"from": 1994306400000,
		"_to": "2033-11-06T05:00:00Z",
		"to": 2014866000000,
		"dst": true,
		"offset": -10800,
		"name": "ADT"
	},
	{
		"_from": "2033-11-06T05:00:00Z",
		"from": 2014866000000,
		"_to": "2034-03-12T06:00:00Z",
		"to": 2025756000000,
		"dst": false,
		"offset": -14400,
		"name": "AST"
	},
	{
		"_from": "2034-03-12T06:00:00Z",
		"from": 2025756000000,
		"_to": "2034-11-05T05:00:00Z",
		"to": 2046315600000,
		"dst": true,
		"offset": -10800,
		"name": "ADT"
	},
	{
		"_from": "2034-11-05T05:00:00Z",
		"from": 2046315600000,
		"_to": "2035-03-11T06:00:00Z",
		"to": 2057205600000,
		"dst": false,
		"offset": -14400,
		"name": "AST"
	},
	{
		"_from": "2035-03-11T06:00:00Z",
		"from": 2057205600000,
		"_to": "2035-11-04T05:00:00Z",
		"to": 2077765200000,
		"dst": true,
		"offset": -10800,
		"name": "ADT"
	},
	{
		"_from": "2035-11-04T05:00:00Z",
		"from": 2077765200000,
		"_to": "2036-03-09T06:00:00Z",
		"to": 2088655200000,
		"dst": false,
		"offset": -14400,
		"name": "AST"
	},
	{
		"_from": "2036-03-09T06:00:00Z",
		"from": 2088655200000,
		"_to": "2036-11-02T05:00:00Z",
		"to": 2109214800000,
		"dst": true,
		"offset": -10800,
		"name": "ADT"
	},
	{
		"_from": "2036-11-02T05:00:00Z",
		"from": 2109214800000,
		"_to": "2037-03-08T06:00:00Z",
		"to": 2120104800000,
		"dst": false,
		"offset": -14400,
		"name": "AST"
	},
	{
		"_from": "2037-03-08T06:00:00Z",
		"from": 2120104800000,
		"_to": "2037-11-01T05:00:00Z",
		"to": 2140664400000,
		"dst": true,
		"offset": -10800,
		"name": "ADT"
	},
	{
		"_from": "2037-11-01T05:00:00Z",
		"from": 2140664400000,
		"_to": "2038-03-14T06:00:00Z",
		"to": 2152159200000,
		"dst": false,
		"offset": -14400,
		"name": "AST"
	},
	{
		"_from": "2038-03-14T06:00:00Z",
		"from": 2152159200000,
		"_to": "2038-11-07T05:00:00Z",
		"to": 2172718800000,
		"dst": true,
		"offset": -10800,
		"name": "ADT"
	},
	{
		"_from": "2038-11-07T05:00:00Z",
		"from": 2172718800000,
		"_to": "2039-03-13T06:00:00Z",
		"to": 2183608800000,
		"dst": false,
		"offset": -14400,
		"name": "AST"
	},
	{
		"_from": "2039-03-13T06:00:00Z",
		"from": 2183608800000,
		"_to": "2039-11-06T05:00:00Z",
		"to": 2204168400000,
		"dst": true,
		"offset": -10800,
		"name": "ADT"
	},
	{
		"_from": "2039-11-06T05:00:00Z",
		"from": 2204168400000,
		"_to": "2040-03-11T06:00:00Z",
		"to": 2215058400000,
		"dst": false,
		"offset": -14400,
		"name": "AST"
	},
	{
		"_from": "2040-03-11T06:00:00Z",
		"from": 2215058400000,
		"_to": "2040-11-04T05:00:00Z",
		"to": 2235618000000,
		"dst": true,
		"offset": -10800,
		"name": "ADT"
	},
	{
		"_from": "2040-11-04T05:00:00Z",
		"from": 2235618000000,
		"_to": "2041-03-10T06:00:00Z",
		"to": 2246508000000,
		"dst": false,
		"offset": -14400,
		"name": "AST"
	},
	{
		"_from": "2041-03-10T06:00:00Z",
		"from": 2246508000000,
		"_to": "2041-11-03T05:00:00Z",
		"to": 2267067600000,
		"dst": true,
		"offset": -10800,
		"name": "ADT"
	},
	{
		"_from": "2041-11-03T05:00:00Z",
		"from": 2267067600000,
		"_to": "2042-03-09T06:00:00Z",
		"to": 2277957600000,
		"dst": false,
		"offset": -14400,
		"name": "AST"
	},
	{
		"_from": "2042-03-09T06:00:00Z",
		"from": 2277957600000,
		"_to": "2042-11-02T05:00:00Z",
		"to": 2298517200000,
		"dst": true,
		"offset": -10800,
		"name": "ADT"
	},
	{
		"_from": "2042-11-02T05:00:00Z",
		"from": 2298517200000,
		"_to": "2043-03-08T06:00:00Z",
		"to": 2309407200000,
		"dst": false,
		"offset": -14400,
		"name": "AST"
	},
	{
		"_from": "2043-03-08T06:00:00Z",
		"from": 2309407200000,
		"_to": "2043-11-01T05:00:00Z",
		"to": 2329966800000,
		"dst": true,
		"offset": -10800,
		"name": "ADT"
	},
	{
		"_from": "2043-11-01T05:00:00Z",
		"from": 2329966800000,
		"_to": "2044-03-13T06:00:00Z",
		"to": 2341461600000,
		"dst": false,
		"offset": -14400,
		"name": "AST"
	},
	{
		"_from": "2044-03-13T06:00:00Z",
		"from": 2341461600000,
		"_to": "2044-11-06T05:00:00Z",
		"to": 2362021200000,
		"dst": true,
		"offset": -10800,
		"name": "ADT"
	},
	{
		"_from": "2044-11-06T05:00:00Z",
		"from": 2362021200000,
		"_to": "2045-03-12T06:00:00Z",
		"to": 2372911200000,
		"dst": false,
		"offset": -14400,
		"name": "AST"
	},
	{
		"_from": "2045-03-12T06:00:00Z",
		"from": 2372911200000,
		"_to": "2045-11-05T05:00:00Z",
		"to": 2393470800000,
		"dst": true,
		"offset": -10800,
		"name": "ADT"
	},
	{
		"_from": "2045-11-05T05:00:00Z",
		"from": 2393470800000,
		"_to": "2046-03-11T06:00:00Z",
		"to": 2404360800000,
		"dst": false,
		"offset": -14400,
		"name": "AST"
	},
	{
		"_from": "2046-03-11T06:00:00Z",
		"from": 2404360800000,
		"_to": "2046-11-04T05:00:00Z",
		"to": 2424920400000,
		"dst": true,
		"offset": -10800,
		"name": "ADT"
	},
	{
		"_from": "2046-11-04T05:00:00Z",
		"from": 2424920400000,
		"_to": "2047-03-10T06:00:00Z",
		"to": 2435810400000,
		"dst": false,
		"offset": -14400,
		"name": "AST"
	},
	{
		"_from": "2047-03-10T06:00:00Z",
		"from": 2435810400000,
		"_to": "2047-11-03T05:00:00Z",
		"to": 2456370000000,
		"dst": true,
		"offset": -10800,
		"name": "ADT"
	},
	{
		"_from": "2047-11-03T05:00:00Z",
		"from": 2456370000000,
		"_to": "2048-03-08T06:00:00Z",
		"to": 2467260000000,
		"dst": false,
		"offset": -14400,
		"name": "AST"
	},
	{
		"_from": "2048-03-08T06:00:00Z",
		"from": 2467260000000,
		"_to": "2048-11-01T05:00:00Z",
		"to": 2487819600000,
		"dst": true,
		"offset": -10800,
		"name": "ADT"
	},
	{
		"_from": "2048-11-01T05:00:00Z",
		"from": 2487819600000,
		"_to": "2049-03-14T06:00:00Z",
		"to": 2499314400000,
		"dst": false,
		"offset": -14400,
		"name": "AST"
	},
	{
		"_from": "2049-03-14T06:00:00Z",
		"from": 2499314400000,
		"_to": "2049-11-07T05:00:00Z",
		"to": 2519874000000,
		"dst": true,
		"offset": -10800,
		"name": "ADT"
	},
	{
		"_from": "2049-11-07T05:00:00Z",
		"from": 2519874000000,
		"_to": "2050-03-13T06:00:00Z",
		"to": 2530764000000,
		"dst": false,
		"offset": -14400,
		"name": "AST"
	},
	{
		"_from": "2050-03-13T06:00:00Z",
		"from": 2530764000000,
		"_to": "2050-11-06T05:00:00Z",
		"to": 2551323600000,
		"dst": true,
		"offset": -10800,
		"name": "ADT"
	},
	{
		"_from": "2050-11-06T05:00:00Z",
		"from": 2551323600000,
		"_to": "9999-12-31T23:59:59Z",
		"to": 253402300799000,
		"dst": false,
		"offset": -14400,
		"name": "AST"
	}
]}