{"_zone": "Indian/Antananarivo",
"zone": [
	{
		"_from": "-9999-01-01T00:00:00Z",
		"from": -377711769600000,
		"_to": "1911-06-30T20:49:56Z",
		"to": -1846293004000,
		"dst": false,
		"offset": 11404,
		"name": "LMT"
	},
	{
		"_from": "1911-06-30T20:49:56Z",
		"from": -1846293004000,
		"_to": "1954-02-27T20:00:00Z",
		"to": -499924800000,
		"dst": false,
		"offset": 10800,
		"name": "EAT"
	},
	{
		"_from": "1954-02-27T20:00:00Z",
		"from": -499924800000,
		"_to": "1954-05-29T20:00:00Z",
		"to": -492062400000,
		"dst": true,
		"offset": 14400,
		"name": "EAST"
	},
	{
		"_from": "1954-05-29T20:00:00Z",
		"from": -492062400000,
		"_to": "9999-12-31T23:59:59Z",
		"to": 253402300799000,
		"dst": false,
		"offset": 10800,
		"name": "EAT"
	}
]}