{"_zone": "Asia/Makassar",
"zone": [
	{
		"_from": "-9999-01-01T00:00:00Z",
		"from": -377711769600000,
		"_to": "1919-12-31T16:02:24Z",
		"to": -1577951856000,
		"dst": false,
		"offset": 28656,
		"name": "LMT"
	},
	{
		"_from": "1919-12-31T16:02:24Z",
		"from": -1577951856000,
		"_to": "1932-10-31T16:02:24Z",
		"to": -1172908656000,
		"dst": false,
		"offset": 28656,
		"name": "MMT"
	},
	{
		"_from": "1932-10-31T16:02:24Z",
		"from": -1172908656000,
		"_to": "1942-02-08T16:00:00Z",
		"to": -880272000000,
		"dst": false,
		"offset": 28800,
		"name": "CIT"
	},
	{
		"_from": "1942-02-08T16:00:00Z",
		"from": -880272000000,
		"_to": "1945-09-22T15:00:00Z",
		"to": -766054800000,
		"dst": false,
		"offset": 32400,
		"name": "JST"
	},
	{
		"_from": "1945-09-22T15:00:00Z",
		"from": -766054800000,
		"_to": "9999-12-31T23:59:59Z",
		"to": 253402300799000,
		"dst": false,
		"offset": 28800,
		"name": "CIT"
	}
]}